{
  "9784715022": [
    {
      "japanese_time": "2026-03-19 04:01:02.667058",
      "pf": "L&L",
      "dom_ooc": "CN",
      "merchant_customer_id": 9784715022,
      "merchant_name": "Robert S Fleming",
      "asin": "B0CX8PX4LN",
      "item_name": "CMD 水泳用 トレーニングチューブ 男女兼用 水泳 チューブ トレーニング パドル スイミングゴム ストレッチバンド 水泳練習用具 収納袋付属(ブルー強度約9.0kg)",
      "cleaned_suppression_reason": "[RULE_DEAL_PRE_DEAL_PRICE_THRESHOLD_NOT_MET]",
      "suppression_category_large": "4.Price Error",
      "suppression_category_medium": "Minimum Deal Price Threshold Not Met",
      "asin_count": 1,
      "t30d_ops": 26269.0,
      "t30d_units": 11.0,
      "t30d_bau_range": "2026-02-09 to 2026-03-02, 2026-03-10 to 2026-03-17",
      "event_range": "2026-03-31 00:00:00 to 2026-04-06 23:59:59"
    },
    {
      "japanese_time": "2026-03-19 04:01:02.667058",
      "pf": "L&L",
      "dom_ooc": "CN",
      "merchant_customer_id": 9784715022,
      "merchant_name": "Robert S Fleming",
      "asin": "B0F21FL6NH",
      "item_name": "CMD 水泳用 トレーニングチューブ 男女兼用 スイミングゴム ストレッチバンド トレーニング パドル 水泳 収納袋付属 トレーニング 用品 (イエロー)",
      "cleaned_suppression_reason": "[RULE_DEAL_PRE_DEAL_PRICE_THRESHOLD_NOT_MET[RULE_DEAL_WAS_BASIS_PRICE_THRESHOLD_NOT_MET[]",
      "suppression_category_large": "4.Price Error",
      "suppression_category_medium": "Was Price Threshold Not Met",
      "asin_count": 1,
      "t30d_ops": 18951.0,
      "t30d_units": 9.0,
      "t30d_bau_range": "2026-02-09 to 2026-03-02, 2026-03-10 to 2026-03-17",
      "event_range": "2026-03-31 00:00:00 to 2026-04-06 23:59:59"
    },
    {
      "japanese_time": "2026-03-19 04:01:02.667058",
      "pf": "L&L",
      "dom_ooc": "CN",
      "merchant_customer_id": 9784715022,
      "merchant_name": "Robert S Fleming",
      "asin": "B0F21F6DZF",
      "item_name": "CMD 水泳用 トレーニングチューブ 男女兼用 スイミングゴム ストレッチバンド トレーニング パドル 水泳 収納袋付属 トレーニング 用品 (ブラック)",
      "cleaned_suppression_reason": "[RULE_DEAL_PRE_DEAL_PRICE_THRESHOLD_NOT_MET[RULE_PROMOTION_ITEM_NOT_APPLIED]",
      "suppression_category_large": "4.Price Error",
      "suppression_category_medium": "Minimum Deal Price Threshold Not Met",
      "asin_count": 1,
      "t30d_ops": 2499.0,
      "t30d_units": 1.0,
      "t30d_bau_range": "2026-02-09 to 2026-03-02, 2026-03-10 to 2026-03-17",
      "event_range": "2026-03-31 00:00:00 to 2026-04-06 23:59:59"
    },
    {
      "japanese_time": "2026-03-19 04:01:02.667058",
      "pf": "L&L",
      "dom_ooc": "CN",
      "merchant_customer_id": 9784715022,
      "merchant_name": "Robert S Fleming",
      "asin": "B0CX8V57M3",
      "item_name": "CMD 水泳用 トレーニングチューブ 男女兼用 水泳 チューブ トレーニング パドル スイミングゴム ストレッチバンド 水泳練習用具 収納袋付属(レッド強度約6.0-7.0kg)",
      "cleaned_suppression_reason": "[RULE_DEAL_PRE_DEAL_PRICE_THRESHOLD_NOT_MET[RULE_PROMOTION_ITEM_NOT_APPLIED]",
      "suppression_category_large": "4.Price Error",
      "suppression_category_medium": "Minimum Deal Price Threshold Not Met",
      "asin_count": 1,
      "t30d_ops": 54966.0,
      "t30d_units": 26.0,
      "t30d_bau_range": "2026-02-09 to 2026-03-02, 2026-03-10 to 2026-03-17",
      "event_range": "2026-03-31 00:00:00 to 2026-04-06 23:59:59"
    }
  ]
}