{
  "576134155302": [
    {
      "asin": "B0DRV7MMM4",
      "item_name": "Melixir (メリクサー公式) ヴィーガンリップトリートメント(4色)、 ツヤ感リップバーム 、ナチュラルカラー、ヴィーガン コラーゲンとホホバオイル配合のディープモイスチャライジングリップケア 15g (3 Pomelo)",
      "suppression_reason": "[]",
      "suppression_category": "1.no suppression",
      "pf": "Consumables",
      "t30d_ops": 22258.66,
      "t30d_units": 14.0
    },
    {
      "asin": "B09Y54LQTP",
      "item_name": "Melixir (メリクサー公式) ヴィーガンリップバター #16 Wine Stain (12色)、ティンテッドリップクリーム、ナチュラルカラー、なめらかな塗り心地、 シアバター配合の保湿リップケア、敏感唇・乾燥唇用、 ビーフリー、 ワセリンフリー、 韓国スキンケア 3.9g",
      "suppression_reason": "[]",
      "suppression_category": "1.no suppression",
      "pf": "Consumables",
      "t30d_ops": 57016.33,
      "t30d_units": 35.0
    },
    {
      "asin": "B0DRV9RWLC",
      "item_name": "Melixir (メリクサー公式) ヴィーガンリップトリートメント 2 Rose ローズ (4色)、 ツヤ感リップバーム 、ナチュラルカラー、ヴィーガン コラーゲンとホホバオイル配合のディープモイスチャライジングリップケア、 敏感唇と乾燥唇用、 韓国メイクアップ 15g",
      "suppression_reason": "[]",
      "suppression_category": "1.no suppression",
      "pf": "Consumables",
      "t30d_ops": 9525.33,
      "t30d_units": 6.0
    },
    {
      "asin": "B09DFJGBKX",
      "item_name": "Melixir (メリクサー公式) ヴィーガンリップバター #12 Caramel (12色)、ティンテッドリップクリーム、ナチュラルカラー、なめらかな塗り心地、 シアバター配合の保湿リップケア、敏感唇・乾燥唇用、 ビーフリー、 ワセリンフリー、 韓国スキンケア 3.9g",
      "suppression_reason": "[]",
      "suppression_category": "1.no suppression",
      "pf": "Consumables",
      "t30d_ops": 307241.69,
      "t30d_units": 185.0
    },
    {
      "asin": "B09DF961QL",
      "item_name": "Melixir（メリクサー公式) ヴィーガンリップバター #11 Autumn Rain (12 色)、ティンテッドリップクリーム、ナチュラルカラー、なめらかな塗り心地、 シアバター配合の保湿リップケア、敏感唇・乾燥唇用、 ビーフリー、 ワセリンフリー、 韓国スキンケア 3.9g",
      "suppression_reason": "[ASIN_BUYABILITY_IS_FALSE[RULE_DEAL_BASIS_PRICE_MISSING[]",
      "suppression_category": "2.OOS",
      "pf": "Consumables",
      "t30d_ops": 264282.38,
      "t30d_units": 159.0
    },
    {
      "asin": "B08XXGZNXP",
      "item_name": "Melixir (メリクサー公式) ヴィーガンリップバター #02 Nudy Rose (12 色)、ティンテッドリップクリーム、ナチュラルカラー、なめらかな塗り心地、 シアバター配合の保湿リップケア、敏感唇・乾燥唇用、 ビーフリー、 ワセリンフリー、 韓国スキンケア 3.9g",
      "suppression_reason": "[]",
      "suppression_category": "1.no suppression",
      "pf": "Consumables",
      "t30d_ops": 389444.48,
      "t30d_units": 234.0
    },
    {
      "asin": "B0DRV776W6",
      "item_name": "Melixir (メリクサー公式) ヴィーガンリップトリートメント(4色)、 ツヤ感リップバーム 、ナチュラルカラー、ヴィーガン コラーゲンとホホバオイル配合のディープモイスチャライジングリップケア 15g (4 Berry)",
      "suppression_reason": "[]",
      "suppression_category": "1.no suppression",
      "pf": "Consumables",
      "t30d_ops": 9285.0,
      "t30d_units": 6.0
    },
    {
      "asin": "B08SBG5Q4N",
      "item_name": "Melixir (メリクサー公式) ヴィーガンリップバター #05 Dewy Rose (12色)、ティンテッドリップクリーム、ナチュラルカラー、なめらかな塗り心地、 シアバター配合の保湿リップケア、敏感唇・乾燥唇用、 ビーフリー、 ワセリンフリー、 韓国スキンケア 3.9g",
      "suppression_reason": "[]",
      "suppression_category": "1.no suppression",
      "pf": "Consumables",
      "t30d_ops": 352488.99,
      "t30d_units": 212.0
    },
    {
      "asin": "B08XXJ5GW9",
      "item_name": "Melixir (メリクサー公式) ヴィーガンリップバター#01 Agave アガベ (クリア) (12色)、ハイドレーティングリップクリーム、なめらかな塗り心地、シアバター入りリップケア、 敏感唇・乾燥唇用、ビーフリー、ワセリンフリー、韓国スキンケア 3.9g",
      "suppression_reason": "[]",
      "suppression_category": "1.no suppression",
      "pf": "Consumables",
      "t30d_ops": 67955.24,
      "t30d_units": 43.0
    },
    {
      "asin": "B08XXGBK6F",
      "item_name": "Melixir (メリクサー公式) ヴィーガンリップバター #03 Red Velvet (12色)、ティンテッドリップクリーム、ナチュラルカラー、なめらかな塗り心地、 シアバター配合の保湿リップケア、敏感唇・乾燥唇用、 ビーフリー、 ワセリンフリー、 韓国スキンケア 3.9g",
      "suppression_reason": "[]",
      "suppression_category": "1.no suppression",
      "pf": "Consumables",
      "t30d_ops": 141667.64,
      "t30d_units": 86.0
    },
    {
      "asin": "B09Y556F43",
      "item_name": "Melixir（メリクサー公式) ヴィーガンリップバター #15 Dirty Pink (12 色)、ティンテッドリップクリーム、ナチュラルカラー、なめらかな塗り心地、 シアバター配合の保湿リップケア、敏感唇・乾燥唇用、 ビーフリー、 ワセリンフリー、 韓国スキンケア 3.9g",
      "suppression_reason": "[]",
      "suppression_category": "1.no suppression",
      "pf": "Consumables",
      "t30d_ops": 64875.62,
      "t30d_units": 39.0
    }
  ]
}